{
  "date": "2026-03-15",
  "generated_at": "2026-03-15 13:51",
  "article_count": 6,
  "subsidiaries": [
    "한화",
    "한화시스템"
  ],
  "press_list": [
    "뉴스1",
    "아시아경제",
    "전자신문",
    "조선비즈",
    "파이낸셜뉴스"
  ],
  "all_subsidiaries": [
    "한화에어로스페이스",
    "한화시스템",
    "한화오션",
    "한화디펜스",
    "한화엔진",
    "한화솔루션",
    "한화토탈에너지스",
    "한화에너지",
    "한화첨단소재",
    "여천NCC",
    "한화생명",
    "한화투자증권",
    "한화저축은행",
    "한화건설",
    "한화갤러리아",
    "한화호텔앤드리조트",
    "한화63시티",
    "한화",
    "한화로보틱스",
    "한화에비에이션",
    "한화비전",
    "한화S&C",
    "한화임팩트"
  ],
  "all_press": [
    "중앙일보",
    "조선일보",
    "한국경제",
    "매일경제",
    "연합뉴스",
    "동아일보",
    "서울경제",
    "이데일리",
    "뉴스1",
    "머니투데이",
    "파이낸셜뉴스",
    "헤럴드경제"
  ],
  "articles": [
    {
      "title": "한화에어로, 美 LNG 20년 장기 계약…\"에너지 안보 강화\"",
      "link": "https://n.news.naver.com/mnews/article/421/0008827171?sid=101",
      "original_link": "https://www.news1.kr/industry/general-industry/6101828",
      "press": "뉴스1",
      "pub_date": "2026-03-15T22:21:00",
      "keyword": "한화에어로스페이스",
      "subsidiary": "한화",
      "summary_lines": [
        "한화에어로스페이스-벤처 글로벌 LNG 구매 계약식(한화에어로스페이스 제공)",
        "계약식에는 손재일 한화에어로스페이스 대표와 마이클 세이블 벤처 글로벌 대표를 비롯해 김정관 산업통상부 장관, 더그 버검 미국 내무부 장관 등 양국 정부 고위 관계자들도 참석했다.",
        "앞서 한화에어로스페이스는 지난달 벤처 글로벌과 2030년부터 20년간 연 150만 톤의 LNG를 공급받는 계약을 체결했는데, 포럼을 계기로 계약식이 열렸다."
      ]
    },
    {
      "title": "한화시스템, KAI 지분 0.58% 샀다…7년 만에 재매입",
      "link": "https://n.news.naver.com/mnews/article/366/0001148672?sid=101",
      "original_link": "https://biz.chosun.com/industry/company/2026/03/15/GYXH3ARSIFDT7BPT7D2TB7ZSIA/?utm_source=naver&utm_medium=original&utm_campaign=biz",
      "press": "조선비즈",
      "pub_date": "2026-03-15T20:23:00",
      "keyword": "한화에어로스페이스",
      "subsidiary": "한화시스템",
      "summary_lines": [
        "방산·우주사업에 주력하고 있는 한화그룹이 경쟁업체인 한국항공우주산업(KAI) 주식을 7년여만에 다시 매입한 것으로 나타났다.",
        "15일 금융감독원 전자공시에 따르면 한화그룹의 방산 계열사인 한화시스템은 지난 13일 공시한 사업보고서에서 지난해 11월 KAI보통주 56만6635주를 599억원에 매입했다고 밝혔다.",
        "이는 KAI전체 주식의 0.58%에 해당하는 규모로, 주식 대량 보유 공시 의무 대상인 5% 미만이라 매입 당시에는 공개되지 않았다."
      ]
    },
    {
      "title": "한화, KAI 지분 0.85% 매입…항공우주·방산분야 협력 강화",
      "link": "https://n.news.naver.com/mnews/article/030/0003407557?sid=101",
      "original_link": "https://www.etnews.com/20260315000095",
      "press": "전자신문",
      "pub_date": "2026-03-15T19:22:00",
      "keyword": "한화에어로스페이스",
      "subsidiary": "한화",
      "summary_lines": [
        "15일 금융감독원 전자공시에 따르면 한화그룹의 방산 계열사인 한화시스템은 지난 13일 공시한 사업보고서에서 지난해 11월 KAI 보통주 56만6635주를 599억원에 매입했다고 밝혔다.",
        "이는 KAI 전체 주식의 0.58%에 해당하는 규모로, 주식 대량 보유 공시 의무 대상인 5% 미만이라 매입 당시에는 공개되지 않았다.",
        "한화그룹이 KAI 지분을 매입한 것은 지난 2018년 한화에어로스페이스가 KAI 지분 5.99%를 전량 매각한 후 7년여 만이다."
      ]
    },
    {
      "title": "[재계 인사이드] 한화오션의 약진을 HD현대가 반기는 이유",
      "link": "https://www.news2day.co.kr/article/20260315500013",
      "original_link": "https://www.news2day.co.kr/article/20260315500013",
      "press": "",
      "pub_date": "2026-03-15T13:08:00",
      "keyword": "한화에어로스페이스",
      "subsidiary": "한화",
      "summary_lines": [
        "[재계 인사이드] 한화오션의 약진을 HD현대가 반기는 이유",
        "[재계 인사이드] 이란전쟁 최대 수혜기업, LIG 넥스원이 회사이름 바꾸는 이유는",
        "[재계 인사이드] 정의선과 정기선의 ‘로봇대전’, 경쟁 그 이상의 의미"
      ]
    },
    {
      "title": "'성장성 가속화' 우주산업에 투자하는 한화 PLUS 우주항공&UAM [이런 펀드 어때요?]",
      "link": "https://n.news.naver.com/mnews/article/014/0005491478?sid=101",
      "original_link": "http://www.fnnews.com/news/202603151041415243",
      "press": "파이낸셜뉴스",
      "pub_date": "2026-03-15T12:50:00",
      "keyword": "한화에어로스페이스",
      "subsidiary": "한화",
      "summary_lines": [
        "15일 금융정보업체 에프앤가이드에 따르면 ‘한화 PLUS 우주항공&UAM’ ETF의 13일 기준 최근 3개월간 수익률은 113.43%에 달한다",
        "최근 1년간 누적 수익률은 176.71%를 가리키고 있다",
        "이 펀드는 지난 2022년 3월 28일 설정됐으며 설정 이후 누적 수익률은 396.71%에 달한다."
      ]
    },
    {
      "title": "1㎜오차도 용납 못해…\"혁신은 일상에서 부터\" 한화오션 명장 1호 박순복[K산업, 미래설계자들]",
      "link": "https://n.news.naver.com/mnews/article/277/0005734426?sid=101",
      "original_link": "https://view.asiae.co.kr/article/2026031315371409812",
      "press": "아시아경제",
      "pub_date": "2026-03-15T11:30:00",
      "keyword": "한화시스템",
      "subsidiary": "한화",
      "summary_lines": [
        "글로벌 시장의 격랑 속에서도 묵묵히 내일을 설계하는 차세대 기술 연구원과 엔지니어들이 있습니다",
        "이들은 대한민국 경제의 실핏줄이자 미래의 한국을 먹여 살릴 진정한 주역들입니다",
        "지난 11일 한화오션 거제사업장에서 만난 박 명장은 \"특수선은 많은 승조원이 탑승하는 함정으로 항상 '내 자식이 이 배에 승선한다'는 마음으로 안전한 함정을 만들기 위해 노력해왔다\"고 말했다."
      ]
    }
  ]
}