{
  "date": "2026-07-24",
  "generated_at": "2026-07-24 12:52",
  "article_count": 6,
  "subsidiaries": [
    "한화"
  ],
  "press_list": [
    "동행미디어 시대",
    "한국경제"
  ],
  "all_subsidiaries": [
    "한화에어로스페이스",
    "한화시스템",
    "한화오션",
    "한화디펜스",
    "한화엔진",
    "한화솔루션",
    "한화토탈에너지스",
    "한화에너지",
    "한화첨단소재",
    "여천NCC",
    "한화생명",
    "한화투자증권",
    "한화저축은행",
    "한화건설",
    "한화갤러리아",
    "한화호텔앤드리조트",
    "한화63시티",
    "한화",
    "한화로보틱스",
    "한화에비에이션",
    "한화비전",
    "한화S&C",
    "한화임팩트"
  ],
  "all_press": [
    "중앙일보",
    "조선일보",
    "한국경제",
    "매일경제",
    "연합뉴스",
    "동아일보",
    "서울경제",
    "이데일리",
    "뉴스1",
    "머니투데이",
    "파이낸셜뉴스",
    "헤럴드경제"
  ],
  "articles": [
    {
      "title": "[비즈투데이] 한화오션, 미 함정 공동 개발 등 조선협력 선도",
      "link": "https://www.obsnews.co.kr/news/articleView.html?idxno=1531766",
      "original_link": "https://www.obsnews.co.kr/news/articleView.html?idxno=1531766",
      "press": "",
      "pub_date": "2026-07-24T20:22:00",
      "keyword": "한화오션",
      "subsidiary": "한화",
      "summary_lines": [
        "한화오션이 미국 내 주요 파트너들과 함정 설계 및 개발, 조선 공급망 구축을 포괄하는 협력 관계를 구축했습니다.",
        "한화오션은 '한미조선협력센터 개소식'을 통해 미국 내 주요 파트너들과 글로벌 전략 수송함 설계 및 개발을 위한 계약 체결 등 MOU 2건 등을 체결했습니다.",
        "한화오션은 또 함정 설계 명가인 '레이도스 깁스 앤 콕스'와 글로벌 전략 수송함 공동 설계를 위한 전문 서비스 계약을 체결했습니다."
      ]
    },
    {
      "title": "HD현대는 AI 조선소·한화는 군함…'마스가' 닻 올렸다",
      "link": "https://n.news.naver.com/mnews/article/015/0005313568?sid=101",
      "original_link": "https://www.hankyung.com/article/2026072449311",
      "press": "한국경제",
      "pub_date": "2026-07-24T17:42:00",
      "keyword": "한화오션",
      "subsidiary": "한화",
      "summary_lines": [
        "정부, 5년간 1200억 R&D 추진",
        "앞서 한·미 양국은 3500억달러(약 513조원) 규모 대미 투자 중 1500억달러(약 220조원)를 조선업에 투입하기로 했다",
        "론 오루크 전 의회조사국(CRS) 해군사무 전문가는 “미국 내 상선 건조를 활성화하려면 컨테이너선 기준 척당 1억5000만~4억달러 규모 보조금을 지급해야 할 것”이라고 말했다."
      ]
    },
    {
      "title": "[기획] 7000억 판 깐 정부…'여수 빅딜' 롯데·한화·DL 적자 털까",
      "link": "https://www.kfenews.co.kr/news/articleView.html?idxno=661194",
      "original_link": "https://www.kfenews.co.kr/news/articleView.html?idxno=661194",
      "press": "",
      "pub_date": "2026-07-24T17:30:00",
      "keyword": "한화솔루션",
      "subsidiary": "한화",
      "summary_lines": [
        "정부와 채권단이 7000억원이 넘는 대규모 패키지 지원을 시작했지만, 중장기 업황 부진 속에서 실질적인 시너지와 수익성 개선을 이끌어낼 수 있을지에 대해서는 신중하게 관망하는 것이 업계의 전반적인 분위기다.",
        "■ 3사 합작법인 출범…범용 에틸렌 139만톤 셧다운",
        "수액백·의료용 LDPE와 포장 점접착제용 POE 등 고부가 신사업에 1500억원을 투입하고, 인프라 및 배관 연결 등에 1032억원을 포함해 총 2532억원 규모의 사업재편 이행투자를 추진할 예정이다."
      ]
    },
    {
      "title": "캐나다 잠수함에 발목, 김동관 '마지막 퍼즐' 향배는?",
      "link": "https://www.peoplewatch.co.kr/article/view/ppw202607070002",
      "original_link": "https://www.peoplewatch.co.kr/article/view/ppw202607070002",
      "press": "",
      "pub_date": "2026-07-24T15:20:00",
      "keyword": "한화오션",
      "subsidiary": "기타",
      "summary_lines": [
        "60조원 사업, 기술력 갖추고도 나토 벽 못넘어",
        "총리는 6일(현지시간) 노바스코샤주 핼리팩스 해군기지에서 우선협상대상자로 독일 티센크루프마린시스템스(TKMS)를 선정했다고 발표했다",
        "총사업비 최대 60조원, 잠수함 12척을 도입하는 캐나다"
      ]
    },
    {
      "title": "'마스가' 시동 건 K조선…한화·HD현대·삼성·HJ, 美와 협력 확대",
      "link": "https://www.etoday.co.kr/news/view/2607103",
      "original_link": "https://www.etoday.co.kr/news/view/2607103",
      "press": "",
      "pub_date": "2026-07-24T11:58:00",
      "keyword": "한화시스템",
      "subsidiary": "한화",
      "summary_lines": [
        "KUSPC는 한미 간 1500억달러 규모 조선 협력 프로젝트인 ‘마스가(MASGA)’의 현지 실행 거점 역할을 맡는다.",
        "미국 콘래드조선소와 공동 개발 중인 1만2000㎥급 LNG 벙커링선은 미국선급협회로부터 기본설계 인증을 받았다.",
        "NH농협금융, 상반기 순익 1조7791억원⋯역대 최대 실적"
      ]
    },
    {
      "title": "한화, 조선 넘어 안보 파트너로…미 군함·골든돔까지 영토 넓힌다",
      "link": "https://n.news.naver.com/mnews/article/417/0001152855?sid=101",
      "original_link": "https://www.sidae.com/article/2026072410021541190",
      "press": "동행미디어 시대",
      "pub_date": "2026-07-24T10:07:00",
      "keyword": "한화디펜스",
      "subsidiary": "한화",
      "summary_lines": [
        "한화필리조선소, 해상 미사일 시험 계측선 수주…MRO 6건·NSMV 5척도 진행",
        "함정·급유함 RFI 회신에 20척 건조능력 확대 계획까지, 미 조선 재건 전방위 협력",
        "보우트 국장은 \"무엇보다도 지속적인 수요 신호가 한화의 필리조선소 투자를 이끌어냈고 이는 오늘날 우리가 맞이하고 있는 해양산업의 새로운 국면과 미국 조선업 재건의 시작을 알렸다\"고 밝혔다."
      ]
    }
  ]
}